simsity/__init__.py
simsity/datasets.py
simsity-0.8.0.dist-info/METADATA
simsity-0.8.0.dist-info/WHEEL
simsity-0.8.0.dist-info/licenses/LICENSE
simsity-0.8.0.dist-info/RECORD
