Metadata-Version: 2.4
Name: simsity
Version: 0.8.0
Summary: A similarity search library
Author: Vincent
License-Expression: MIT
License-File: LICENSE
Requires-Python: >=3.8
Requires-Dist: numpy>2
Requires-Dist: polars
Provides-Extra: dev
Requires-Dist: marimo; extra == 'dev'
Requires-Dist: model2vec; extra == 'dev'
Requires-Dist: pytest>=7.0; extra == 'dev'
